{
  "name": "fritzing-parts-finder",
  "dependencies": {
    "bluebird": "registry:npm/bluebird#3.4.1+20160811213708",
    "chalk": "registry:npm/chalk#1.1.1+20160812215109",
    "glob": "registry:npm/glob#6.0.0+20160723033700",
    "simple-git": "registry:npm/simple-git#1.47.0+20160823074737"
  },
  "globalDependencies": {
    "commander": "registry:dt/commander#2.3.0+20160317120654",
    "node": "registry:env/node#4.0.0+20160824014937",
    "xml2js": "registry:dt/xml2js#0.0.0+20160317120654"
  }
}
